fusion/__init__.py
fusion/api_client.py
fusion/configuration.py
fusion/rest.py
fusion/api/__init__.py
fusion/api/arrays_api.py
fusion/api/availability_zones_api.py
fusion/api/default_api.py
fusion/api/hardware_types_api.py
fusion/api/host_access_policies_api.py
fusion/api/identity_manager_api.py
fusion/api/network_interface_groups_api.py
fusion/api/network_interfaces_api.py
fusion/api/operations_api.py
fusion/api/placement_groups_api.py
fusion/api/protection_policies_api.py
fusion/api/regions_api.py
fusion/api/role_assignments_api.py
fusion/api/roles_api.py
fusion/api/snapshots_api.py
fusion/api/storage_classes_api.py
fusion/api/storage_endpoints_api.py
fusion/api/storage_services_api.py
fusion/api/tenant_spaces_api.py
fusion/api/tenants_api.py
fusion/api/volume_snapshots_api.py
fusion/api/volumes_api.py
fusion/api/workload_planner_api.py
fusion/models/__init__.py
fusion/models/api_client.py
fusion/models/api_client_post.py
fusion/models/array.py
fusion/models/array_list.py
fusion/models/array_patch.py
fusion/models/array_post.py
fusion/models/array_ref.py
fusion/models/availability_zone.py
fusion/models/availability_zone_list.py
fusion/models/availability_zone_post.py
fusion/models/availability_zone_ref.py
fusion/models/error.py
fusion/models/error_response.py
fusion/models/hardware_type.py
fusion/models/hardware_type_list.py
fusion/models/hardware_type_ref.py
fusion/models/host_access_policies_post.py
fusion/models/host_access_policy.py
fusion/models/host_access_policy_list.py
fusion/models/host_access_policy_ref.py
fusion/models/iscsi.py
fusion/models/list_response_fields.py
fusion/models/network_interface.py
fusion/models/network_interface_eth.py
fusion/models/network_interface_fc.py
fusion/models/network_interface_group.py
fusion/models/network_interface_group_eth.py
fusion/models/network_interface_group_eth_post.py
fusion/models/network_interface_group_list.py
fusion/models/network_interface_group_patch.py
fusion/models/network_interface_group_post.py
purefusion-1.2.0.dist-info/LICENSE
purefusion-1.2.0.dist-info/METADATA
purefusion-1.2.0.dist-info/WHEEL
purefusion-1.2.0.dist-info/top_level.txt
purefusion-1.2.0.dist-info/RECORD
