Metadata-Version: 2.1
Name: purefusion
Version: 1.2.0
Summary: Pure Fusion API
Home-page: 
Author-email: 
Keywords: Swagger,Pure Fusion API
License-File: LICENSE
Requires-Dist: PyJWT (>=2.3.0)
Requires-Dist: cryptography (>=3.4.8)
Requires-Dist: requests
Requires-Dist: paramiko
Requires-Dist: urllib3 (>=1.15)
Requires-Dist: six (>=1.10)
Requires-Dist: certifi
Requires-Dist: python-dateutil
